punits/__init__.py
punits/__main__.py
punits/app.py
punits/consts/__init__.py
punits/consts/conversions/__init__.py
punits/consts/conversions/data_consts.py
punits/consts/conversions/length_consts.py
punits/consts/conversions/mass_consts.py
punits/consts/conversions/siprefix.py
punits/consts/conversions/temperature_consts.py
punits/consts/conversions/volume_consts.py
punits/consts/labels/__init__.py
punits-0.2.dist-info/LICENSE.md
punits-0.2.dist-info/METADATA
punits-0.2.dist-info/WHEEL
punits-0.2.dist-info/top_level.txt
punits-0.2.dist-info/RECORD
