Metadata-Version: 2.1
Name: punits
Version: 0.2
Summary: A simple utility to convert values between different units
Home-page: https://github.com/ju-sh/punits
Author: Julin S
Author-email: julins@cannottellyou.yet
License: UNKNOWN
Project-URL: Changelog, https://github.com/ju-sh/punits/blob/master/CHANGELOG.md
Project-URL: Issue Tracker, https://github.com/ju-sh/punits/issues
Platform: UNKNOWN
Classifier: Programming Language :: Python :: 3
Classifier: License :: OSI Approved :: MIT License
Classifier: Operating System :: OS Independent
Classifier: Topic :: Utilities
Classifier: Development Status :: 2 - Pre-Alpha
Classifier: Natural Language :: English
Requires-Python: >=3.6
